pytijo_cli/__init__.py
pytijo_cli/cli.py
pytijo_cli/push.py
pytijo_cli-0.0.5.dist-info/METADATA
pytijo_cli-0.0.5.dist-info/WHEEL
pytijo_cli-0.0.5.dist-info/entry_points.txt
pytijo_cli-0.0.5.dist-info/top_level.txt
pytijo_cli-0.0.5.dist-info/zip-safe
pytijo_cli-0.0.5.dist-info/RECORD
