Metadata-Version: 2.1
Name: pytijo-cli
Version: 0.0.5
Summary: Tijo Command line interface
Home-page: http://tijo.io
Author: Jon Castro
Author-email: jon@tijo.io
License: LICENSE
Platform: UNKNOWN
Classifier: Intended Audience :: Developers
Classifier: Intended Audience :: Information Technology
Classifier: Intended Audience :: System Administrators
Classifier: License :: OSI Approved :: Apache Software License
Classifier: Operating System :: POSIX :: Linux
Classifier: Programming Language :: Python
Classifier: Programming Language :: Python :: 2
Classifier: Programming Language :: Python :: 2.7
Classifier: Programming Language :: Python :: 2.6
Requires-Dist: click
Requires-Dist: pytijo
Requires-Dist: pytijo-api-client
